Workbook

Sheet Dashboard
A1: DASHBOARD — PROPRIEDADE INTELECTUAL | IFMA
A2: Atualizado em: 04/04/2026 | Fonte: INPI / NIT-IFMA
A3: Total de PIs | E3: Patentes | I3: Softwares | M3: Concedidas/Cert.
A5: =COUNTA(Dados!B3:B5000) -> 191 | E5: =COUNTIF(Dados!B:B,"Patente de Invenção")+COUNTIF(Dados!B:B,"Modelo de Utilidade") -> 64 | I5: =COUNTIF(Dados!B:B,"Software") -> 87 | M5: =COUNTIF(Dados!H:H,"Concedida")+COUNTIF(Dados!H:H,"Certificado Emitido") -> 88

Sheet Indicadores
A1: Total por Tipo de PI | D1: Por Status | G1: Depósitos por Ano | J1: Ranking por Campus
A2: Patente de Invenção | B2: =COUNTIF(Dados!B:B,"Patente de Invenção") -> 48 | D2: Certificado Emitido | E2: =COUNTIF(Dados!H:H,"Certificado Emitido") -> 79 | G2: 2009 | H2: =SUMPRODUCT((ISNUMBER(SEARCH("2009",Dados!G:G)))*1) -> 2 | J2: Monte Castelo | K2: =COUNTIF(Dados!D:D,"Monte Castelo") -> 49
A3: Modelo de Utilidade | B3: =COUNTIF(Dados!B:B,"Modelo de Utilidade") -> 16 | D3: Concedida | E3: =COUNTIF(Dados!H:H,"Concedida") -> 9 | G3: 2010 | H3: =SUMPRODUCT((ISNUMBER(SEARCH("2010",Dados!G:G)))*1) -> 0 | J3: Imperatriz | K3: =COUNTIF(Dados!D:D,"Imperatriz") -> 25
A4: Software | B4: =COUNTIF(Dados!B:B,"Software") -> 87 | D4: Deferida | E4: =COUNTIF(Dados!H:H,"Deferida") -> 1 | G4: 2011 | H4: =SUMPRODUCT((ISNUMBER(SEARCH("2011",Dados!G:G)))*1) -> 0 | J4: Reitoria | K4: =COUNTIF(Dados!D:D,"Reitoria") -> 19
A5: Marca | B5: =COUNTIF(Dados!B:B,"Marca") -> 34 | D5: Em andamento | E5: =COUNTIF(Dados!H:H,"Em andamento") -> 39 | G5: 2012 | H5: =SUMPRODUCT((ISNUMBER(SEARCH("2012",Dados!G:G)))*1) -> 2 | J5: Caxias | K5: =COUNTIF(Dados!D:D,"Caxias") -> 11
A6: Desenho Industrial | B6: =COUNTIF(Dados!B:B,"Desenho Industrial") -> 6 | D6: Em exame | E6: =COUNTIF(Dados!H:H,"Em exame") -> 0 | G6: 2013 | H6: =SUMPRODUCT((ISNUMBER(SEARCH("2013",Dados!G:G)))*1) -> 0 | J6: Araioses | K6: =COUNTIF(Dados!D:D,"Araioses") -> 11
A7: TOTAL | B7: =SUM(B2:B6) -> 191 | D7: Depositado | E7: =COUNTIF(Dados!H:H,"Depositado") -> 35 | G7: 2014 | H7: =SUMPRODUCT((ISNUMBER(SEARCH("2014",Dados!G:G)))*1) -> 1 | J7: Açailândia | K7: =COUNTIF(Dados!D:D,"Açailândia") -> 13
D8: Aguardando Certificado | E8: =COUNTIF(Dados!H:H,"Aguardando Certificado") -> 1 | G8: 2015 | H8: =SUMPRODUCT((ISNUMBER(SEARCH("2015",Dados!G:G)))*1) -> 7 | J8: Timon | K8: =COUNTIF(Dados!D:D,"Timon") -> 5
D9: Indeferida | E9: =COUNTIF(Dados!H:H,"Indeferida") -> 9 | G9: 2016 | H9: =SUMPRODUCT((ISNUMBER(SEARCH("2016",Dados!G:G)))*1) -> 0 | J9: Grajaú | K9: =COUNTIF(Dados!D:D,"Grajaú") -> 3
D10: Arquivada | E10: =COUNTIF(Dados!H:H,"Arquivada") -> 11 | G10: 2017 | H10: =SUMPRODUCT((ISNUMBER(SEARCH("2017",Dados!G:G)))*1) -> 1 | J10: Maracanã | K10: =COUNTIF(Dados!D:D,"Maracanã") -> 2
D11: Anulado | E11: =COUNTIF(Dados!H:H,"Anulado") -> 5 | G11: 2018 | H11: =SUMPRODUCT((ISNUMBER(SEARCH("2018",Dados!G:G)))*1) -> 6 | J11: Codó | K11: =COUNTIF(Dados!D:D,"Codó") -> 8
D12: Em sigilo | E12: =COUNTIF(Dados!H:H,"Em sigilo") -> 2 | G12: 2019 | H12: =SUMPRODUCT((ISNUMBER(SEARCH("2019",Dados!G:G)))*1) -> 9 | J12: São José de Ribamar | K12: =COUNTIF(Dados!D:D,"São José de Ribamar") -> 2
G13: 2020 | H13: =SUMPRODUCT((ISNUMBER(SEARCH("2020",Dados!G:G)))*1) -> 18 | J13: São João dos Patos | K13: =COUNTIF(Dados!D:D,"São João dos Patos") -> 1
G14: 2021 | H14: =SUMPRODUCT((ISNUMBER(SEARCH("2021",Dados!G:G)))*1) -> 14 | J14: Centro Histórico | K14: =COUNTIF(Dados!D:D,"Centro Histórico") -> 2
G15: 2022 | H15: =SUMPRODUCT((ISNUMBER(SEARCH("2022",Dados!G:G)))*1) -> 14 | J15: Alcântara | K15: =COUNTIF(Dados!D:D,"Alcântara") -> 0
G16: 2023 | H16: =SUMPRODUCT((ISNUMBER(SEARCH("2023",Dados!G:G)))*1) -> 13 | J16: Barra do Corda | K16: =COUNTIF(Dados!D:D,"Barra do Corda") -> 0
G17: 2024 | H17: =SUMPRODUCT((ISNUMBER(SEARCH("2024",Dados!G:G)))*1) -> 42 | J17: Cotitular | K17: =COUNTIF(Dados!D:D,"Cotitular") -> 1
G18: 2025 | H18: =SUMPRODUCT((ISNUMBER(SEARCH("2025",Dados!G:G)))*1) -> 46 | J18: Não informado | K18: =COUNTIF(Dados!D:D,"Não informado") -> 32
G19: 2026 | H19: =SUMPRODUCT((ISNUMBER(SEARCH("2026",Dados!G:G)))*1) -> 11

Sheet Dados
A1: IFMA — REGISTRO DE PROPRIEDADE INTELECTUAL
A2: # | B2: Tipo | C2: Título | D2: Campus | E2: Autor(es) | F2: Nº do Processo | G2: Data de Depósito | H2: Status | I2: Data do Status | J2: Observações
A3: 1 | B3: Desenho Industrial | C3: PADRÃO ORNAMENTAL APLICADO A/EM JOGO DE CARTAS | D3: Açailândia | E3: DAILSON COELHO ABREU | F3: BR 30 2024 001621 2 | G3: 04/04/2024 | H3: Indeferida
A4: 2 | B4: Desenho Industrial | C4: ESTOJOS DE BARALHO | D4: Açailândia | E4: DAILSON COELHO ABREU | F4: BR 32 2025 000148 2 | G4: 14/01/2025 | H4: Indeferida
A5: 3 | B5: Desenho Industrial | C5: PEÇAS DE TABULEIRO | D5: Açailândia | E5: RAIFRAN ABIDIMAR DE CASTRO | F5: BR 30 2025 008736 8 | G5: 18/12/2025 | H5: Depositado
A6: 4 | B6: Desenho Industrial | C6: FICHAS PARA JOGOS | D6: Açailândia | E6: DAILSON COELHO ABREU | F6: BR 30 2025 007116 0 | G6: 21/10/2025 | H6: Depositado
A7: 5 | B7: Desenho Industrial | C7: SUPORTES PARA CARTAS [PARA JOGOS DE CARTAS] | D7: Açailândia | E7: DAILSON COELHO ABREU | F7: BR 30 2025 007118 6 | G7: 21/10/2025 | H7: Depositado
A8: 6 | B8: Desenho Industrial | C8: PADRÃO ORNAMENTAL APLICADO A/FOTOGRAFIA | D8: Monte Castelo | E8: IVANA MÁRCIA OLIVEIRA MAIA | F8: BR 30 2024 001932 7 | G8: 23/04/2024 | H8: Concedida
A9: 7 | B9: Marca | C9: PoliTeCs Políticas Públicas, Tecnologias Sociais e Ações Mitigadoras para Sociedade do século XXI | D9: Açailândia | E9: RAIFRAN ABIDIMAR | F9: 937675342 | G9: 16/01/2025 | H9: Depositado
A10: 8 | B10: Marca | C10: CidBeeS Gestão Democrático-Participativa de Cidades e Sustentabilidade Socioambiental | D10: Açailândia | E10: RAIFRAN ABIDIMAR | F10: 937676101 | G10: 16/01/2025 | H10: Depositado
A11: 9 | B11: Marca | C11: SiiGiT- NCL 28 | D11: Açailândia | E11: RAIFRAN ABIDIMAR | F11: 937675024 | G11: 16/01/2025 | H11: Depositado
A12: 10 | B12: Marca | C12: SiiGiT- NCL 41 | D12: Açailândia | E12: RAIFRAN ABIDIMAR | F12: 937674702 | G12: 16/01/2025 | H12: Depositado
A13: 11 | B13: Marca | C13: Deck Parasite | D13: Açailândia | E13: DAILSON COELHO ABREU | F13: 933640714 | G13: 26/02/2024 | H13: Deferida | J13: Protocolado cumprimento de exigência em 19/11/2025
A14: 12 | B14: Marca | C14: DanTUS Degradação Ambiental, Territorialização e Sustentabilidade | D14: Açailândia | E14: IFMA | F14: 934427151 | G14: 30/04/2024 | H14: Concedida | J14: Concessão de Registro. Renovar registro em 2035.
A15: 13 | B15: Marca | C15: InterPoIS Geopolítica, Desenvolvimento Socioeconômico e Sustentabilidade | D15: Açailândia | E15: IFMA | F15: 934426970 | G15: 30/04/2024 | H15: Depositado | J15: exame de mérito
A16: 14 | B16: Marca | C16: MERMÃS DIGITAIS | D16: IMPERATRIZ | E16: SIMONE AZEVEDO/ LAILLA GALENO | F16: 933678290 | G16: 28/02/2024 | H16: Concedida | J16: exame de mérito
A17: 15 | B17: Marca | C17: TEIA DESIGN LAB - NCL 9 | D17: Monte Castelo | E17: CAMILA ANDRADE DOS SANTOS | F17: 940468603 | G17: 06/08/2025 | H17: Depositado | J17: Protocolada
A18: 16 | B18: Marca | C18: TEIA DESIGN LAB - NCL 41 | D18: Monte Castelo | E18: CAMILA ANDRADE DOS SANTOS | F18: 940469138 | G18: 06/08/2025 | H18: Depositado | J18: Protocolada
A19: 17 | B19: Marca | C19: TEIA DESIGN LAB - NCL 42 | D19: Monte Castelo | E19: CAMILA ANDRADE DOS SANTOS | F19: 940468980 | G19: 06/08/2025 | H19: Depositado | J19: Protocolada
A20: 18 | B20: Marca | C20: buddy robotics | D20: Monte Castelo | E20: MARCELO EUGENIO | F20: 938447343 | G20: 21/03/2025 | H20: Depositado
A21: 19 | B21: Marca | C21: PPGCA Programa de Pós-Graduação em Computação Aplicada | D21: Monte Castelo | E21: OMAR ANDRES CARMONA CORTES | F21: 938448226 | G21: 21/03/2025 | H21: Depositado
A22: 20 | B22: Marca | C22: LABENSAIOS-Laboratório de Ensaios Mecânicos e Termomecânicos | D22: Monte Castelo | E22: SAMUEL FILGUEIRAS RODRIGUES | F22: 938486594 | G22: 25/03/2025 | H22: Depositado
A23: 21 | B23: Marca | C23: AÇAÍMOV | D23: Não informado | E23: BREHME D NAPOLI REIS DE MESQUITA | F23: 935644822 | G23: 01/08/2024 | H23: Depositado | J23: exame de mérito
A24: 22 | B24: Marca | C24: Fabrica de Inovação | D24: Reitoria | E24: IFMA | F24: 930353870 | G24: 08/05/2023 | H24: Concedida | J24: Concessão de Registro. Renovar regsitro em 2034.
A25: 23 | B25: Marca | C25: Editora IFMA | D25: Reitoria | E25: IFMA | F25: 930353862 | G25: 08/05/2023 | H25: Concedida | J25: Concessão de Registro. Renovar regsitro em 2033.
A26: 24 | B26: Marca | C26: [re]design | D26: Reitoria | E26: IFMA | F26: 942372620 | G26: 09/01/2026 | H26: Depositado | J26: Protocolada
A27: 25 | B27: Marca | C27: Innovation factory | D27: Reitoria | E27: IFMA | F27: 936573295 | G27: 10/10/2024 | H27: Depositado | J27: protocolada
A28: 26 | B28: Marca | C28: Innovation factory | D28: Reitoria | E28: IFMA | F28: 936572736 | G28: 10/10/2024 | H28: Depositado | J28: protocolada
A29: 27 | B29: Marca | C29: NÚCLEO DE DESIGN E TECNOLOGIAS DA INFORMAÇÃO E COMUNICAÇÃO | D29: Reitoria | E29: IFMA | F29: 942995031 | G29: 11/03/2026 | H29: Depositado | J29: Protocolada
A30: 28 | B30: Marca | C30: Astronomia no Sertão | D30: Reitoria | E30: IFMA | F30: 930393848 | G30: 11/05/2023 | H30: Concedida | J30: Registro deferido. Aguardando pagamento da taxa de concessão do registro.
A31: 29 | B31: Marca | C31: SETE PERGUNTAS PODCAST | D31: Reitoria | E31: IFMA | F31: 937659738 | G31: 15/01/2025 | H31: Depositado | J31: Publicado para apresentação de oposição
A32: 30 | B32: Marca | C32: IFMA AFIRMATIVO | D32: Reitoria | E32: IFMA | F32: 942276795 | G32: 23/12/2025 | H32: Depositado | J32: Protocolada
A33: 31 | B33: Marca | C33: IFMA LIVRE DE VIOLÊNCIA DE GÊNERO | D33: Reitoria | E33: IFMA | F33: 942241649 | G33: 23/12/2025 | H33: Depositado | J33: Protocolada
A34: 32 | B34: Marca | C34: IFMA NO MUNDO | D34: Reitoria | E34: IFMA | F34: 942276949 | G34: 23/12/2025 | H34: Depositado | J34: Protocolada
... A40: 38 | B40: Marca | C40: Processo Eletrônico Projeto Estratégico | D40: Reitoria | E40: IFMA | F40: 942277422 | G40: 23/12/2025 | H40: Depositado | J40: Protocolada
A41: 39 | B41: Marca | C41: Mara BIOTECH | D41: São José de Ribamar | E41: FABIA HOLANDA DE BRITO | F41: 939116278 | G41: 13/05/2025 | H41: Depositado
A42: 40 | B42: Marca | C42: IFMA CAST - NCL38 | D42: Timon | E42: NARA SUELLEN LEONCIO CHAVES | F42: 940468433 | G42: 06/08/2025 | H42: Depositado | J42: Protocolada
A43: 41 | B43: Modelo de Utilidade | C43: DISPOSITIVO DE PROTEÇÃO E HIGIENIZAÇÃO/DESINFECÇÃO PARA ESPONJAS DE COZINHA | D43: Araioses | E43: LUIS MESQUITA DE SOUSA FILHO | F43: BR 10 2020 005111 3 | G43: 13/03/2020 | H43: Em andamento | J43: O pedido foi notificado pelo INPI na RPI nº 2827, de 11/03/25, onde foi apontado falta de novidade / atividade inventiva, apresentando anterioridades muito similares. Após reunião com os inventores, no dia 24/03/25, ficou claro que não haveria possib
A44: 42 | B44: Modelo de Utilidade | C44: PRENSA TÉRMICA PARA PLASTIFICAÇÃO E MISTURA COMPACTA DE MATERIAL POLIMÉRICO | D44: Codó | E44: BRUNO LEONARDY SOUSA LOPES | F44: BR 20 2022 000265 2 | G44: 07/01/2022 | H44: Em andamento
A45: 43 | B45: Modelo de Utilidade | C45: CAIXA MODULAR RÍGIDA DE CRIAÇÃO RACIONAL DE ABELHAS SEM FERRÃO | D45: GRA | E45: LUIZ OTÁVIO DE OLIVEIRA SOUZA JUNIOR | F45: BR 10 2026 005212 4 | G45: 05/03/2026 | H45: Em andamento
A46: 44 | B46: Modelo de Utilidade | C46: DISPOSITIVO PORTÁTIL PARA A EXTRAÇÃO DE MEL DE ABELHAS NATIVAS SEM FERRÃO | D46: GRA | E46: WEVERTON FILGUEIRA PACHECO | F46: BR 20 2026 007835 8 | G46: 31/03/2026 | H46: Em andamento
A47: 45 | B47: Modelo de Utilidade | C47: POSTO DE TRABALHO ERGONÔMICO PARA QUEBRADEIRAS DE COCO BABAÇU | D47: Monte Castelo | E47: SCHEILA REGINA GOMES ALVES | F47: BR 20 2021 008801 5 | G47: 05/05/2021 | H47: Arquivada | J47: Foi arquivada em 17/09/2019 (BR 20 2019 010913 6), por falta de cumprimento de exigência na data de 23/07/2017, porém foi REDEPOSITADA na com nova numeração BR 20 2021 008801 5 e está publicada/ativa no INPI. PAGAMENTO DE ANUIDADE SOLICITADO
A48: 46 | B48: Modelo de Utilidade | C48: APARELHO ERGOMÉTRICO PARA A REALIZAÇÃO DE ATIVIDADES FÍSICAS POR PARAPLÉGICOS | D48: Monte Castelo | E48: KEYLL CARLOS RIBEIRO MARTINS (PATENTE CONCEDIDA) | F48: BR 20 2019 000491 1 | G48: 10/01/2019 | H48: Em sigilo | J48: ATIVO/SIGILO
A49: 47 | B49: Modelo de Utilidade | C49: BICICLETA ERGOMÉTRICA PARA CADEIRANTES | D49: Monte Castelo | E49: KEYLL CARLOS RIBEIRO MARTINS | F49: BR 20 2021 000594 2 | G49: 13/01/2021 | H49: Em andamento | J49: ATIVA
A50: 48 | B50: Modelo de Utilidade | C50: DETECTOR DE FALHAS NO ABASTECIMENTO DE POSTOS DE COMBUSTÍVEIS | D50: Monte Castelo | E50: LUCILENE FERREIRA MOUZINHO | G50: 15/12/2015 | H50: Em andamento | J50: 6.22 Exigência preliminar - pedidos sem buscas realizadas por outros Escritórios de Patentes/ cumprimento de exigência realizado enviado 29/04/2022
A51: 49 | B51: Modelo de Utilidade | C51: ARMADILHA LUMINOSA SOLAR ENTOMOLÓGICA | D51: Monte Castelo | E51: CARLOS MAGNO DOS ANJOS VERAS | F51: BR 10 2024 024123 1 | G51: 20/11/2024 | H51: Em andamento
A52: 50 | B52: Modelo de Utilidade | C52: “SISTEMA DE SECAGEM EM PEQUENA ESCALA DE BIOMATERIAIS PRODUZIDOS PELO MÉTODO CASTING” | D52: Monte Castelo | E52: JOSILENE LIMA SERRA | F52: BR 20 2025 010203 5 | G52: 21/05/2025 | H52: Em andamento
A53: 51 | B53: Modelo de Utilidade | C53: MÁQUINA DE BANCADA PARA A OBTENÇÃO DE FIBRAS POLIMÉRICAS POR FUSÃO | D53: Monte Castelo | E53: GRICIRENE SOUSA CORREIA | F53: BR 20 2024 017113 1 | G53: 21/08/2024 | H53: Anulado | J53: Pedido com numeração anulada (depósito não reconhecido pelo INPI por erros formais). Corrigir os erros com a professora e proceder com novo depósito.
A54: 52 | B54: Modelo de Utilidade | C54: MÁQUINA DE BANCADA PARA A OBTENÇÃO DE FIBRAS POLIMÉRICAS POR FUSÃO | D54: Monte Castelo | E54: GRICIRENE SOUSA CORREIA | F54: BR 20 2025 013149 3 | G54: 25/06/2025 | H54: Em andamento
A55: 53 | B55: Modelo de Utilidade | C55: MODELO DE UTILIDADE DE SISTEMA DE SECAGEM EM PEQUENA ESCALA DE BIOMATERIAIS PRODUZIDOS PELO MÉTODO CASTING | D55: Monte Castelo | E55: JOSILENE LIMA SERRA | F55: BR 20 2026 007804 8 | G55: 31/03/2026 | H55: Em andamento
A56: 54 | B56: Modelo de Utilidade | C56: “ANTENA DE CIRCUITO IMPRESSO ESPIRAL FLEXÍVEL APLICADA A INTERNET DAS COISAS DE BANDA ESTREITA” | D56: Não informado | E56: PAULO HENRIQUE BEZERRA DE CARVALHO | F56: BR 10 2023 025152 8 | G56: 30/11/2023 | H56: Em andamento | J56: PATENTE CO-TITULAR COM UEMA E UFMA
A57: 55 | B57: Modelo de Utilidade | C57: APARELHO DE COMUNICAÇÃO LUMINOSA | D57: PFR | E57: WELINGTON DOMINGOS ALVES | F57: BR 20 2021 020267 5 | G57: 08/10/2021 | H57: Em andamento
A58: 56 | B58: Modelo de Utilidade | C58: CABINE DE DESINFECÇÃO INDIVIDUAL | D58: São José de Ribamar | E58: LETÍCIA CABRAL CORREIA | F58: BR 10 2020 013779 4 | G58: 06/07/2020 | H58: Em andamento | J58: ATIVA
A59: 57 | B59: Patente de Invenção | C59: NOVA ROTA DE SÍNTESE DE L-TRIPTOFANO COM ÁCIDO FUMÁRICO HIDRATADO | D59: ACA | E59: JHONATAM DE OLIVEIRA CARVALHO | F59: BR 10 2024 003752 9 | G59: 26/02/2024 | H59: Em andamento
A60: 58 | B60: Patente de Invenção | C60: BIODIESEL A PARTIR DO ÓLEO DE COCO BABAÇU (ORBIGNYA SPECIOSA MART.) | D60: Imperatriz | E60: ANA ANGÉLICA MATHIAS MACÊDO | F60: BR 10 2021 004768 2 | H60: Em andamento | J60: ATIVA
A61: 59 | B61: Patente de Invenção | C61: BIODIESEL A PARTIR DO AZEITE DE COCO BABAÇU (Orbignya speciosa Mart.) | D61: Imperatriz | E61: ANA ANGÉLICA MATHIAS MACÊDO | F61: BR 10 2021 004720 8 | H61: Em andamento | J61: ATIVA
A62: 60 | B62: Patente de Invenção | C62: FILME COMPÓSITO POLIMÉRICO COM CRISTAL COMPLEXADO DE AMINOÁCIDO E PROCESSO DE OBTENÇÃO | D62: Imperatriz | E62: ANA ANGÉLICA MATHIAS MACÊDO | F62: BR 10 2019 013701 0 | G62: 01/01/1970 | H62: Indeferida | J62: 9.2 Indeferimento Pedido indeferido por falta de manifestação ao parecer técnico publicado pelo INPI. O pedido não atendia ao requisito de novidade, em decorrência da reivindicação 1 já ter sido antecipada por documentos e não caber alteração do tex
A63: 61 | B63: Patente de Invenção | C63: ÁGUA AROMATIZADA | D63: Imperatriz | E63: ANA ANGÉLICA MATHIAS MACÊDO | F63: BR 10 2021 003920 5 | G63: 01/03/2021 | H63: Em andamento | J63: ATIVA
A64: 62 | B64: Patente de Invenção | C64: PROCESSO PARA PRODUÇÃO DE ISOLANTE ELÉTRICO CONTENDO MINERAL MICA E GALACTOMANANA | D64: Imperatriz | E64: ANA ANGÉLICA MATHIAS MACÊDO | F64: BR 10 2018 006775 3 | G64: 04/04/2018 | H64: Indeferida | J64: 9.2. INDEFERIMENTO. A pesquisadora foi informada. Estamos aguardando retorno do documento para protocolar recurso do indeferimento. PRAZO: 08/11.
A65: 63 | B65: Patente de Invenção | C65: MICROESFERAS DE QUITOSANA COM CRISTAL TERNÁRIO DE COBRE (II) COMPLEXADO COM 1,10-FENANTROLINA E L- TIROSINA | D65: Imperatriz | E65: ANA ANGÉLICA MATHIAS MACÊDO | F65: BR 10 2022 008725 3 | G65: 05/05/2022 | H65: Em andamento
A66: 64 | B66: Patente de Invenção | C66: SÍNTESE DE UM CRISTAL EMISSOR DE LUZ VERMELHA FORMADO POR L-TREONINA DOPADA COM Eu3+ PARA APLICAÇÃO EM MARCADORES BIOLUMINESCENTES | D66: Imperatriz | E66: ANA ANGÉLICA MATHIAS MACÊDO | F66: BR 10 2021 004353 9 | G66: 08/03/2021 | H66: Em andamento | J66: ATIVA
A67: 65 | B67: Patente de Invenção | C67: MICROESFERAS DE QUITOSANA COMPLEXADAS A METAIS DE TRANSIÇÃO | D67: Imperatriz | E67: ANA ANGÉLICA MATHIAS MACÊDO | F67: BR 10 2021 004422 5 | G67: 09/03/2021 | H67: Em andamento | J67: ATIVA
A68: 66 | B68: Patente de Invenção | C68: MICROESFERAS REVESTIDAS COM ALGINATO DE SÓDIUM À BASE DE CRISTAIS DE L-TREONINA E COBALTO (II) PARA APLICAÇÃO COMO SENSOR DE TEMPERATURA | D68: Imperatriz | E68: ANA ANGÉLICA MATHIAS MACÊDO (CARTA PATENTE CONCEDIDA) | F68: BR 10 2020 000741 6 | G68: 13/01/2020 | H68: Concedida | J68: CARTA PATENTE EXPEDIDA EM 06/05/2025. OBSERVAR OS CÓDIGOS DE PAGAMENTO DE ANUIDADE DE PATENTE DE INVENÇÃO REFERENTE AO ANO.
A69: 67 | B69: Patente de Invenção | C69: CRISTAL DE CLOROBROMETO DE BIS-GLICINA E SEU USO | D69: Imperatriz | E69: ANA ANGÉLICA MATHIAS MACÊDO | F69: BR 10 2021 016065 9 | G69: 13/08/2021 | H69: Em andamento | J69: Pedido depositado pela UFMA. Não encontramos e-mail informando o depósito ou enviando procuração para depósito.
A70: 68 | B70: Patente de Invenção | C70: NOVO CRISTAL TERNÁRIO DE 1,10 FENANTROLINA E LMETIONINA COMPLEXADO COM COBRE (II) COM POTENCIAL INIBITÓRIO PARA CÉLULAS CANCERÍGENAS | D70: Imperatriz | E70: ANA ANGÉLICA MATHIAS MACÊDO | F70: BR 10 2020 000797 1 | G70: 14/01/2020 | H70: Em andamento | J70: ATIVA
A71: 69 | B71: Patente de Invenção | C71: PREPARAÇÃO DE MICROESFERAS REVESTIDAS DE ALGINATO DE SÓDIO A BASE DE CRISTAIS DE L-VALINA COMPLEXADAS COM ÍONS DE NÍQUEL (II) APLICADAS COMO MICRONUTRIENTES PARA PLANTAS | D71: Imperatriz | E71: ANA ANGÉLICA MATHIAS MACÊDO | F71: BR 10 2020 000877 3 | G71: 15/01/2020 | H71: Em andamento | J71: ATIVA
A72: 70 | B72: Patente de Invenção | C72: PROCESSO METODOLÓGICO PARA O PREPARO DO AGENTE ANTITUMORAL DE Cu(II) COM GLICINA E 1,10-FENANTROLINA NA FORMA CRISTALINA DISPERSO EM QUITOSANA PARA OBTENÇÃO DE FILMES INORGÂNICOS BIODEGRADÁVEIS | D72: Imperatriz | E72: ANA ANGÉLICA MATHIAS MACÊDO | F72: BR 10 2020 000904 4 | G72: 15/01/2020 | H72: Em andamento | J72: ATIVA
A73: 71 | B73: Patente de Invenção | C73: COLA ISOLANTE ELÉTRICA BIODEGRADÁVEL | D73: Imperatriz | E73: ANA ANGÉLICA MATHIAS MACÊDO | F73: BR 10 2018 071282 9 | G73: 16/10/2018 | H73: Indeferida | J73: INDEFERIDA
A74: 72 | B74: Patente de Invenção | C74: MICROESFERAS DE ALGINATO COMPLEXADAS A METAIS DE TRANSIÇÃO | D74: Imperatriz | E74: ANA ANGÉLICA MATHIAS MACÊDO | F74: BR 10 2018 076272 9 | G74: 17/12/2018 | H74: Indeferida | J74: 9.2 Indeferimento. Indeferido o pedido por não atender aos requisitos legais, conforme parecer técnico. A cópia do parecer técnico poderá ser solicitada através do formulário modelo 1.05. Desta data corre o prazo de 60 (sessenta) dias para eventual
A75: 73 | B75: Patente de Invenção | C75: CAPACITORES BIOCOMPATÍVEIS A PARTIR DE MATERIAL VEGETAL | D75: Imperatriz | E75: ANA ANGÉLICA | F75: BR 10 2024 012499 5 | G75: 19/06/2024 | H75: Em andamento
A76: 74 | B76: Patente de Invenção | C76: EMBALAGEM BIODEGRADÁVEL REFORÇADA COM RESÍDUOS DE ACEROLA E PROCESSO DE OBTENÇÃO DO MESMO | D76: Imperatriz | E76: ANA ANGÉLICA | F76: BR 10 2024 012536 3 | G76: 19/06/2024 | H76: Em andamento | J76: Protocolado cumprimento de exigência.
A77: 75 | B77: Patente de Invenção | C77: FILME BIODEGRADÁVEL À BASE DE CASCA DE BANANA E GALACTOMANA EXTRAÍDA DE SEMENTES DE Adenanthera pavonina L. | D77: Imperatriz | E77: ANA ANGÉLICA MATHIAS MACÊDO (PATENTE CONCEDIDA) | F77: BR 10 2018 001266 5 | G77: 22/01/2018 | H77: Concedida | J77: Problema: A 3ª anuidade que tinha prazo 22/01/2020 a 22/04/2020 (ordinário) e 23/04/2020 a 22/10/2020 (extraordinário), foi pago no ano de 2021, totalmente fora do prazo já entrando para a 4ª anuidade. Abrir Fale conosco informando que foi efetuado p
A78: 76 | B78: Patente de Invenção | C78: PROCESSO DE RETICULAÇÃO DE FIBRAS NATURAIS | D78: Imperatriz | E78: ANA ANGÉLICA | F78: BR 10 2024 022026 9 | G78: 23/10/2024 | H78: Em andamento | J78: AGUARDANDO PUBLICAÇÃO
A79: 77 | B79: Patente de Invenção | C79: FILME PARA REVESTIMENTO DE PRÓTESE VASCULAR E PROCESSO DE OBTENÇÃO | D79: Imperatriz | E79: ANA ANGÉLICA MATHIAS MACÊDO | F79: BR 10 2020 003923 7 | G79: 27/02/2020 | H79: Em andamento | J79: ATIVA
A80: 78 | B80: Patente de Invenção | C80: PASTA PARA CIMENTO ODONTOLÓGICO E PROCESSO DE OBTENÇÃO | D80: Imperatriz | E80: ANA ANGÉLICA MATHIAS MACÊDO | F80: BR 10 2020 004042 1 | G80: 28/02/2020 | H80: Em andamento | J80: ATIVA
A81: 79 | B81: Patente de Invenção | C81: HIDROCOLÓIDE CICATRIZANTE E ANTIMICROBIANO À BASE DE GALACTOMANANA E SEU PROCESSO DE OBTENÇÃO | D81: Imperatriz | E81: ANA ANGÉLICA MATHIAS MACÊDO | F81: 118579 U | G81: 28/03/2023 | H81: Em andamento | J81: PATENTE CO-TITULAR COM O INOPOL
A82: 80 | B82: Patente de Invenção | C82: FILME CRISTALINO DE L-TREONINA COM COBRE (II) E GALACTOMANANA | D82: Imperatriz | E82: ANA ANGÉLICA MATHIAS MACÊDO | F82: BR 10 2019 010859 2 | G82: 28/05/2019 | H82: Em sigilo | J82: ATIVO/SIGILO
A83: 81 | B83: Patente de Invenção | C83: HIDROCOLÓIDE CICATRIZANTE E ANTIMICROBIANO À BASE DE GALACTOMANANA E SEU PROCESSO DE OBTENÇÃO | D83: Imperatriz | E83: ANA ANGÉLICA MATHIAS MACEDO | F83: BR 10 2025 021075 4 | G83: 30/09/2025 | H83: Em andamento
A84: 82 | B84: Patente de Invenção | C84: BEBIDA ALCOÓLICA A BASE DE MESOCARPO DE BABAÇU | D84: Maracanã | E84: SILVIO CARLOS COELHO | F84: BR 10 2020 004314 5 | G84: 03/03/2020 | H84: Anulado | J84: NUMERAÇÃO ANULADA. Em analise pela UFMA para retornar ou não o deposito
A85: 83 | B85: Patente de Invenção | C85: PROCESSO DE OBTENÇÃO DE AGUARDENTE A PARTIR DE AMIDO | D85: Maracanã | E85: FRANCISCO ALBUQUERQUE BASTOS | F85: BR 10 2017 015770 9 | G85: 24/07/2017 | H85: Indeferida | J85: Publicação 7.1 (RPI 2696 - 06/09/2022). Conhecimento de parecer técnico. Suspenso o andamento do pedido para que o depositante se manifeste, no prazo de 90 (noventa) dias desta data (05/12/2022), quanto ao contido no parecer técnico. A cópia do parec
A86: 84 | B86: Patente de Invenção | C86: FORNO PARA REFUSÃO DE ALUMÍNIO UTILIZANDO AQUECIMENTO POR IRRADIAÇÃO DE MICRO-ONDAS | D86: Monte Castelo | E86: JOMAR SALES VASCONCELOS | F86: PI 0920084-3 | G86: 01/12/2009 | H86: Arquivada | J86: ARQUIVADA/INDEFERIDAS PELO INPI
A87: 85 | B87: Patente de Invenção | C87: FORMULAÇÃO DE SABONETE E HIDRATANTE OBTIDO A PARTIR DO EXTRATO HIDROALCOÓLICO DE Humiria balsamifera | D87: Monte Castelo | E87: GEORGIANA EURIDES DE CARVALHO MARQUES | F87: BR 10 2021 004387 3 | G87: 09/03/2021 | H87: Em andamento | J87: ATIVA
A88: 86 | B88: Patente de Invenção | C88: FORMULAÇÃO DE SABONETE E HIDRATANTE OBTIDO A PARTIR DO EXTRATO ALCOÓLICO À BASE DE FOLHAS DE Duguetia furfuracea (A.St.-Hil.) Saf. | D88: Monte Castelo | E88: GEORGIANA EURIDES DE CARVALHO MARQUES | F88: BR 10 2023 008837 6 | G88: 09/05/2023 | H88: Em andamento
A89: 87 | B89: Patente de Invenção | C89: TIJOLO CERÂMICO REFRATÁRIO E PROCESSO DE OBTENÇÃODO MESMO | D89: Monte Castelo | E89: ADRIANO LOURO ROCHA | F89: BR 10 2026 000761 7 | G89: 13/01/2026 | H89: Em andamento
A90: 88 | B90: Patente de Invenção | C90: CATALISADORES TRIMETÁLICOS OBTIDOS POR COMBUSTÃO ASSISTIDA POR MICRO-ONDAS PARA REFORMA CATALÍTICA DO METANO | D90: Monte Castelo | E90: GILVAN PEREIRA DE FIGUEREDO | F90: BR 10 2020 007306 0 | G90: 13/04/2020 | H90: Em andamento | J90: ATIVO
A91: 89 | B91: Patente de Invenção | C91: PRENSA ISOSTÁTICA E BANCADA MÓVEL DE PRENSA ISOSTÁTICA | D91: Monte Castelo | E91: JOSÉ MANUEL RIVAS MERCURY (PATENTE CONCEDIDA) | F91: BR 10 2015 031419 1 | G91: 15/12/2015 | H91: Concedida | J91: ATIVO/CNPJ ANTIGO. Aguardando a expedição da carta-patente
A92: 90 | B92: Patente de Invenção | C92: PROCESSO DE EXTRAÇÃO DE DNA GENÔMICO DE FUNGOS FILAMENTOSOS E LEVEDURIFORMES | D92: Monte Castelo | E92: CRISTINA DE ANDRADE MONTEIRO | F92: BR 10 2015 0314922 | G92: 16/12/2015 | H92: Indeferida | J92: 9.2.4 - Mantido o indeferimento, uma vez que não foi apresentado recurso dentro do prazo legal. RPI 2752, de 03/10/2023.
A93: 91 | B93: Patente de Invenção | C93: KIT DE CONVERSÃO PAR MOTORIZAÇÃO EM CADEIRAS DE RODAS MECANOMANUAL | D93: Monte Castelo | E93: KEYLL CARLOS RIBEIRO MARTINS | F93: BR 10 2015 031573 2 | G93: 16/12/2015 | H93: Arquivada | J93: Pesquisador notificado no dia 16/03. Servidor deu ciência. Arquivar Patente. 9.2 Indeferimento. Indeferido o pedido por não atender aos requisitos legais, conforme parecer técnico. A cópia do parecer técnico poderá ser solicitada através do formulári
A94: 92 | B94: Patente de Invenção | C94: COMBINAÇÕES E FORMULAÇÕES ANTIFÚNGICAS A BASE DE CINAMALDEIDO | D94: Monte Castelo | E94: CRISTINA DE ANDRADE MONTEIRO | F94: BR 10 2020 023723 3 | G94: 20/11/2020 | H94: Arquivada | J94: Existem duas numerações anuladas BR 10 2019 013198 0/BR 10 2020 004393 5 po falta de cumprimento de exigência, foi REDEPOSITADA EM 13/01/2021- BR 20 2021 000594 2 ATIVO NO INPI. NUMERAÇÃO ANULADA (PESQUISADORA NOTIFICADA NO DIA 26/05/21 DA EXIGÊNCIA,
A95: 93 | B95: Patente de Invenção | C95: DISPOSITIVO SENSORIAL OLFATIVO APLICADO Á DETERMINAÇÃO DE CONTAMINANTES NO LEITE | D95: Monte Castelo | E95: JOMAR SALES VASCONCELOS | F95: BR 10 2015 029541 3 | G95: 23/11/2015 | H95: Indeferida | J95: Não atende à disposição do artigo 25 da LPI, por apresentar falta de precisão e clareza no quadro reivindicatório e contraria o artigo 8° combinado com o art. 13 da LPI, por conter reivindicações apresentando falta do requisito de patenteabilidade pa
A96: 94 | B96: Patente de Invenção | C96: DISPOSITIVO ELETRÔNICO OLFATIVO APLICADO À CARACTERIZAÇÃO DE SUBPRODUTOS DE BIODIESEL | D96: Monte Castelo | E96: JOMAR SALES VASCONCELOS | F96: BR 10 2015 029527 8 | G96: 23/11/2015 | H96: Arquivada | J96: ARQUIVADA/INDEFERIDAS PELO INPI
A97: 95 | B97: Patente de Invenção | C97: MÉTODO PARA SINTERIZAÇÃO DE CERÂMICAS VARISTORAS EM FORNO MICRO-ONDAS ADAPTADO | D97: Monte Castelo | E97: JOMAR SALES VASCONCELOS | F97: PI 0903171-5 | G97: 26/05/2009 | H97: Arquivada | J97: ARQUIVADA/INDEFERIDAS PELO INPI
A98: 96 | B98: Patente de Invenção | C98: DISPOSITIVO ELETRÔNICO PORTÁTIL PARA DESINFECÇÃO DE CONDICIONADORES DE AR | D98: Monte Castelo | E98: KIANY SIRLEY BRANDÃO CAVALCANTE | F98: BR 10 2015 012887 8 | G98: 26/05/2015 | H98: Arquivada | J98: Pesquisadores não retornaram exigência do INPI no prazo hábil. AGIFMA sugeriu mudança para MU mas não foi feita a adequação.
A99: 97 | B99: Patente de Invenção | C99: PROCESSO DE OBTENÇÃO DE SENSOR OLFATIVO ARTIFICIAL PARA ANÁLISE DA QUALIDADE DE BIODIESEL | D99: Monte Castelo | E99: JOMAR SALES VASCONCELOS | F99: BR 10 2012 019700 6 | G99: 26/07/2012 | H99: Arquivada | J99: ARQUIVADA/INDEFERIDAS PELO INPI
A100: 98 | B100: Patente de Invenção | C100: PROCESSO DE OBTENÇÃO DE FILME BACTERICIDA BASEADO EM DIÓXIDO DE TITÂNIO NANOMÉTRICO | D100: Monte Castelo | E100: JOMAR SALES VASCONCELOS | F100: BR 10 2012 013934 0 | G100: 30/05/2012 | H100: Arquivada | J100: ARQUIVADA/INDEFERIDAS PELO INPI
A101: 99 | B101: Patente de Invenção | C101: FORMULAÇÕES BIOLARVICIDAS À BASE DA NANOEMULSÃO DO ÓLEO ESSENCIAL DE Dizygostemon riparius | D101: Monte Castelo | E101: CLENILMA MARQUES BRANDÃO | F101: BR 10 2025 021078 9 | G101: 30/09/2025 | H101: Em andamento
A102: 100 | B102: Patente de Invenção | C102: nan | D102: Não informado | E102: LEGENDAS | F102: nan | H102: Em andamento
A103: 101 | B103: Patente de Invenção | C103: DISPOSITIVO DE CONTROLE SEMAFÓRICO UTILIZANDO LÓGICA DIFUSA EMBARCADA | D103: Não informado | E103: ALEXANDRE SALES VASCONCELOS | F103: BR 10 2014 033131 0 A2 | G103: 19/12/2014 | H103: Arquivada | J103: ARQUIVADA/INDEFERIDAS PELO INPI
A104: 102 | B104: Patente de Invenção | C104: COMPÓSITO DE POLIANILINA/FERRITA DE ZINCO, SEU PROCESSO DE OBTENÇÃO E SEU USO COMO SENSOR DE GÁS FOTOTERMICAMENTE ESTIMULADO | D104: Não informado | E104: GRICIRENE SOUSA CORREIA | F104: BR 10 2026 004204 8 | G104: 23/02/2026 | H104: Em andamento
A105: 103 | B105: Patente de Invenção | C105: UNIVERSO IF | D105: Reitoria | E105: CTIT | F105: 909098590 | H105: Arquivada | J105: ARQUIVADA
...
